bsite/__init__.py
bsite/bb.py
bsite-1.1.dist-info/METADATA
bsite-1.1.dist-info/WHEEL
bsite-1.1.dist-info/top_level.txt
bsite-1.1.dist-info/RECORD
