Metadata-Version: 2.1
Name: bsite
Version: 1.1
Summary: bsite是用于采集B站用户视频列表页、视频评论数据的python包。 https://github.com/thunderhit/bsite
Home-page: https://github.com/hidadeng/bsite
Author: 大邓
Author-email: thunderhit@qq.com
License: MIT
Keywords: data collect,数据采集,bilibili
Platform: UNKNOWN
Requires-Python: >=3.5
Requires-Dist: requests
